html_validator
tiddlyeditor_plus
space
gadget
room_script
tiddlywebplugins
rtf
test
tiddlywiki_validator
