Metadata-Version: 1.0
Name: tiddlywebplugins.tiddlydocs
Version: 0.11
Summary: Packaging of Tiddlydocs
Home-page: http://pypi.python.org/pypi/tiddlywebplugins.tiddlydocs
Author: simonmcmanus
Author-email: mcmanus.simon@gmail.com
License: UNKNOWN
Platform: Posix; MacOS X; Windows
